{"name":"Probless","tagline":"","body":"probless\r\n========\r\n\r\n**progless** is a web app which aims to minimize problems as less as possible.\r\n\r\nThis app collects problems from anyone and binds the problems to others who can give advice or solve the problems.\r\n\r\nPlease note that this app is still under construction.\r\nOnce this app is available, this app will have version number.","google":"UA-39368753-1","note":"Don't delete this file! It's used internally to help with page regeneration."}